graph_parse/__init__.py
graph_parse/enums.py
graph_parse/helpers.py
graph_parse/main.py
graph_parse/models.py
graph_parse-0.3.1.dist-info/WHEEL
graph_parse-0.3.1.dist-info/METADATA
graph_parse-0.3.1.dist-info/RECORD
