Metadata-Version: 2.1
Name: graph-parse
Version: 0.3.1
Summary: 
Author: james
Author-email: jamesnarayanrao@gmail.com
Requires-Python: >=3.10.5,<4.0.0
Classifier: Programming Language :: Python :: 3
Requires-Dist: coverage (>=6.4.4,<7.0.0)
Requires-Dist: mypy
Requires-Dist: pydantic
Requires-Dist: pydash
Requires-Dist: pytest
